piban/__init__.py
piban/constants.py
piban/exceptions.py
piban/piban.py
piban/utils.py
piban-0.0.1.dist-info/LICENSE
piban-0.0.1.dist-info/METADATA
piban-0.0.1.dist-info/WHEEL
piban-0.0.1.dist-info/top_level.txt
piban-0.0.1.dist-info/RECORD
