Metadata-Version: 2.1
Name: piban
Version: 0.0.1
Summary: A Python IBAN validation tool
Home-page: https://github.com/juanjsebgarcia/piban
Author: Juan Garcia Alvite
License: MIT
Classifier: License :: OSI Approved :: MIT License
Classifier: Programming Language :: Python :: 3
Classifier: Programming Language :: Python :: 3.8
Requires-Python: >=3.8
License-File: LICENSE
